pdf_masking_library/__init__.py
pdf_masking_library/__main__.py
pdf_masking_library/app.py
pdf_masking_library/logger_config.py
pdf_masking_library/ocr_extraction.py
pdf_masking_library/pdf_processing.py
pdf_masking_library/utils.py
pdf_masking_library-0.1.5.dist-info/METADATA
pdf_masking_library-0.1.5.dist-info/WHEEL
pdf_masking_library-0.1.5.dist-info/top_level.txt
pdf_masking_library-0.1.5.dist-info/RECORD
